easytesting/__init__.py
easytesting/run_test.py
easytesting/singleton.py
easytesting/test_case.py
easytesting/metrics/__init__.py
easytesting/metrics/bert_score_check.py
easytesting/metrics/bert_score_similarity_check.py
easytesting/metrics/max_nodes_number_check.py
easytesting/metrics/max_question_number_check.py
easytesting/metrics/metric.py
easytesting/metrics/min_nodes_number_check.py
easytesting/metrics/min_question_number_check.py
easytesting/metrics/randomscore.py
easytesting/metrics/rouge_similarity_check.py
easy_testing-0.2.2.dist-info/LICENSE
easy_testing-0.2.2.dist-info/METADATA
easy_testing-0.2.2.dist-info/WHEEL
easy_testing-0.2.2.dist-info/top_level.txt
easy_testing-0.2.2.dist-info/RECORD
