Metadata-Version: 2.1
Name: easy-testing
Version: 0.2.2
Summary: Framework for testing
Home-page: https://github.com/IreneSoligno/easy-testing
Author: Irene Soligno
Author-email: irene.s@docsity.com
License: MIT
Classifier: License :: OSI Approved :: MIT License
Classifier: Operating System :: OS Independent
Classifier: Programming Language :: Python :: 3.6
Classifier: Programming Language :: Python :: 3.7
Classifier: Programming Language :: Python :: 3.8
Classifier: Programming Language :: Python :: 3.9
Classifier: Programming Language :: Python :: 3.10
Classifier: Topic :: Software Development :: Libraries :: Application Frameworks
Classifier: Topic :: Software Development :: Libraries :: Python Modules
Requires-Python: ~=3.6
License-File: LICENSE
Requires-Dist: openai >=0.28.0
Requires-Dist: evaluate ==0.4.1
Requires-Dist: bert-score ==0.3.13
Requires-Dist: rouge-score ==0.1.2
Requires-Dist: absl-py ==2.0.0
